breviar/__init__.py
breviar/entrypoint.py
breviar/cli/__init__.py
breviar/cli/constants.py
breviar/cli/errors.py
breviar/cli/main.py
breviar/cli/text.py
breviar/cli/utils.py
breviar/cli/providers/__init__.py
breviar/cli/providers/bilty.py
breviar/core/__init__.py
breviar/core/errors.py
breviar/core/main.py
breviar/core/utils.py
breviar/core/providers/__init__.py
breviar/core/providers/bitly.py
breviar-0.0.1rc0.dist-info/LICENSE
breviar-0.0.1rc0.dist-info/METADATA
breviar-0.0.1rc0.dist-info/WHEEL
breviar-0.0.1rc0.dist-info/entry_points.txt
breviar-0.0.1rc0.dist-info/top_level.txt
breviar-0.0.1rc0.dist-info/RECORD
