Metadata-Version: 2.1
Name: breviar
Version: 0.0.1rc0
Summary: URL shortener cli
Home-page: UNKNOWN
Author: Damir Chanyshev
Author-email: hairygeek@yandex.com
License: UNKNOWN
Project-URL: Bug Tracker, https://github.com/hairygeek/breviar
Project-URL: Documentation, https://github.com/hairygeek/breviar
Project-URL: Source Code, https://github.com/hairygeek/breviar
Keywords: link url shortener cli bilty
Platform: UNKNOWN
Requires-Dist: colorama (>=0.4.3)
Requires-Dist: click (>=7.1.1)
Requires-Dist: cerberus (>=1.3.2)
Requires-Dist: requests (>=2.0)
